<?xml version="1.0" encoding="utf-8" ?>
<dwsync>
<file name="index.php" server="home290177727.1and1-data.host" local="131733670737905118" remote="131733670200000000" />
<file name="trabajos.php" server="home290177727.1and1-data.host" local="131731162669788369" remote="131731162800000000" />
<file name="scripts.js" server="home290177727.1and1-data.host" local="131733812433510186" remote="131733812400000000" />
<file name="estilos.css" server="home290177727.1and1-data.host" local="131733761306867354" remote="131733760800000000" />
<file name="salida.php" server="home290177727.1and1-data.host" local="131728713707096868" remote="131728713600000000" />
<file name="menus.php" server="home290177727.1and1-data.host" local="131733758937172507" remote="131733758400000000" />
<file name="veamos.php" server="home290177727.1and1-data.host" local="131737955386260495" remote="131737955400000000" />
<file name="contacto.php" server="home290177727.1and1-data.host" local="131731200777882260" remote="131731200600000000" />
<file name="entretenimiento.php" server="home290177727.1and1-data.host" local="131733758736418350" remote="131733759600000000" />
<file name="50x15.swf" server="home290177727.1and1-data.host" local="131733702336494388" remote="131733702000000000" />
<file name="abstracto.html" server="home290177727.1and1-data.host" local="131733702336544592" remote="131733702000000000" />
<file name="abstracto.swf" server="home290177727.1and1-data.host" local="131733702336674232" remote="131733702000000000" />
<file name="cochefu4-1.swf" server="home290177727.1and1-data.host" local="131733702336743715" remote="131733702000000000" />
<file name="cochefu4.swf" server="home290177727.1and1-data.host" local="131733702336823853" remote="131733702000000000" />
<file name="comodines.swf" server="home290177727.1and1-data.host" local="131733702336853404" remote="131733702000000000" />
<file name="comparador.swf" server="home290177727.1and1-data.host" local="131733702337003002" remote="131733702600000000" />
<file name="cuantas.swf" server="home290177727.1and1-data.host" local="131733702337033335" remote="131733702600000000" />
<file name="cuantas.txt" server="home290177727.1and1-data.host" local="131733702337072881" remote="131733702600000000" />
<file name="dibujando.swf" server="home290177727.1and1-data.host" local="131733702337123373" remote="131733702600000000" />
<file name="fallo.swf" server="home290177727.1and1-data.host" local="131733702337192873" remote="131733702600000000" />
<file name="graficoPublico.swf" server="home290177727.1and1-data.host" local="131733702337282271" remote="131733702600000000" />
<file name="laberinto.swf" server="home290177727.1and1-data.host" local="131733702337390396" remote="131733702600000000" />
<file name="marcador.swf" server="home290177727.1and1-data.host" local="131733702337440280" remote="131733702600000000" />
<file name="parchis.swf" server="home290177727.1and1-data.host" local="131733702337518301" remote="131733702600000000" />
<file name="parEso.swf" server="home290177727.1and1-data.host" local="131733702337608150" remote="131733702600000000" />
<file name="preguntas.xml" server="home290177727.1and1-data.host" local="131733702337667899" remote="131733702600000000" />
<file name="preguntas1.xml" server="home290177727.1and1-data.host" local="131733702337727873" remote="131733702600000000" />
<file name="preguntas2.xml" server="home290177727.1and1-data.host" local="131733702337801165" remote="131733702600000000" />
<file name="preguntas3.xml" server="home290177727.1and1-data.host" local="131733702338152264" remote="131733702600000000" />
<file name="preguntas4.xml" server="home290177727.1and1-data.host" local="131733702338201762" remote="131733702600000000" />
<file name="preguntas5.xml" server="home290177727.1and1-data.host" local="131733702338284503" remote="131733702600000000" />
<file name="preguntas6.xml" server="home290177727.1and1-data.host" local="131733702338334783" remote="131733702600000000" />
<file name="relojeria.swf" server="home290177727.1and1-data.host" local="131733702338394228" remote="131733702600000000" />
<file name="rosa.swf" server="home290177727.1and1-data.host" local="131733702338484357" remote="131733702600000000" />
</dwsync>